portfoliocraft/Asset_Selection_Formulation.py
portfoliocraft/__init__.py
portfoliocraft-0.1.2.dist-info/METADATA
portfoliocraft-0.1.2.dist-info/WHEEL
portfoliocraft-0.1.2.dist-info/top_level.txt
portfoliocraft-0.1.2.dist-info/RECORD
